pybookmarks/__init__.py
pybookmarks/main.py
pybookmarks/static.py
pybookmarks/utils.py
pybookmarks-0.0.2.dist-info/LICENSE
pybookmarks-0.0.2.dist-info/METADATA
pybookmarks-0.0.2.dist-info/WHEEL
pybookmarks-0.0.2.dist-info/entry_points.txt
pybookmarks-0.0.2.dist-info/top_level.txt
pybookmarks-0.0.2.dist-info/RECORD
